

[{"vid":"BT12218290145","name":"basic truck","current_port":"3946148604","fuel_capacity":53000.0,"current_fuel":50000.0,"carrying_capacity":8.0},
{"vid":"BT89436132105","name":"basic truck","current_port":"5546694512","fuel_capacity":53000.0,"current_fuel":7000.0,"carrying_capacity":8.0},
{"vid":"BT34422955333","name":"basic truck","current_port":"8933154789","fuel_capacity":53000.0,"current_fuel":26000.0,"carrying_capacity":8.0},
{"vid":"BT45961089777","name":"basic truck","current_port":"8933154789","fuel_capacity":53000.0,"current_fuel":49000.0,"carrying_capacity":8.0}]